AutoTrans/__init__.py
AutoTrans/cli.py
AutoTrans/index - 副本.html
AutoTrans/index.html
AutoTrans/index2024.html
AutoTrans/run_AutoTrans.bat
AutoTrans/test.ipynb
AutoTrans/__pycache__/__init__.cpython-312.pyc
AutoTrans/static/custom.css
AutoTrans/static/io.js
AutoTrans/static/shorten-prompt.js
AutoTrans/static/slides.js
AutoTrans/static/text-format.js
AutoTrans(server)/__init__.py
AutoTrans(server)/cli.py
AutoTrans-2025.2.22.dist-info/METADATA
AutoTrans-2025.2.22.dist-info/WHEEL
AutoTrans-2025.2.22.dist-info/entry_points.txt
AutoTrans-2025.2.22.dist-info/top_level.txt
AutoTrans-2025.2.22.dist-info/RECORD
