Metadata-Version: 2.2
Name: AutoTrans
Version: 2025.2.22
Summary: Automating the entire translation process with LLM
Author: Jinbiao Yang
Author-email: ray306@gmail.com
Keywords: LLM,chatgpt,translation,automator
Classifier: Development Status :: 4 - Beta
Classifier: Intended Audience :: Science/Research
Classifier: License :: OSI Approved :: GNU General Public License (GPL)
Classifier: Programming Language :: Python :: 3
Requires-Dist: pandas
Requires-Dist: jinja2
Requires-Dist: fastapi
Requires-Dist: deepl
Requires-Dist: nltk
Requires-Dist: pyperclip
Requires-Dist: uvicorn
Requires-Dist: toml
Requires-Dist: langchain
Requires-Dist: langchain_openai
Dynamic: author
Dynamic: author-email
Dynamic: classifier
Dynamic: keywords
Dynamic: requires-dist
Dynamic: summary
